lfilterpy/__init__.py
lfilterpy/http/__init__.py
lfilterpy/http/filter.py
lfilterpy-0.1.3.dist-info/LICENSE
lfilterpy-0.1.3.dist-info/METADATA
lfilterpy-0.1.3.dist-info/WHEEL
lfilterpy-0.1.3.dist-info/top_level.txt
lfilterpy-0.1.3.dist-info/RECORD
