Metadata-Version: 2.1
Name: lfilterpy
Version: 0.1.3
Summary: Manage website visit
Home-page: https://github.com/dcloud347/lfilter
Author: dcloud347
Author-email: 17864201683@163.com
License: LICENSE
Platform: UNKNOWN
License-File: LICENSE
